discover_jenkins/__init__.py
discover_jenkins/results.py
discover_jenkins/runner.py
discover_jenkins/settings.py
discover_jenkins/utils.py
discover_jenkins/tasks/__init__.py
discover_jenkins/tasks/pylint.rc
discover_jenkins/tasks/run_flake8.py
discover_jenkins/tasks/run_jshint.py
discover_jenkins/tasks/run_pep8.py
discover_jenkins/tasks/run_pylint.py
discover_jenkins/tasks/run_sloccount.py
discover_jenkins/tasks/with_coverage.py
django_discover_jenkins-0.1.2.dist-info/DESCRIPTION.rst
django_discover_jenkins-0.1.2.dist-info/METADATA
django_discover_jenkins-0.1.2.dist-info/pydist.json
django_discover_jenkins-0.1.2.dist-info/RECORD
django_discover_jenkins-0.1.2.dist-info/top_level.txt
django_discover_jenkins-0.1.2.dist-info/WHEEL
