Metadata-Version: 2.0
Name: django-discover-jenkins
Version: 0.1.2
Summary: A minimal fork of django-jenkins designed to work with the discover runner, made with simplicity in mind
Home-page: https://github.com/lincolnloop/django-discover-jenkins
Author: Brandon Konkle
Author-email: brandon@lincolnloop.com
License: BSD
Keywords: django,discover,runner,jenkins,hudson
Platform: UNKNOWN
Classifier: Development Status :: 3 - Alpha
Classifier: Environment :: Web Environment
Classifier: Framework :: Django
Classifier: License :: OSI Approved :: BSD License
Classifier: Operating System :: OS Independent
Classifier: Programming Language :: JavaScript
Classifier: Programming Language :: Python :: 2.7
Classifier: Topic :: Internet :: WWW/HTTP
Classifier: Topic :: Internet :: WWW/HTTP :: Dynamic Content
Classifier: Topic :: Software Development :: Libraries :: Python Modules
